setup.cfg
setup.py
UsbLamp.egg-info/PKG-INFO
UsbLamp.egg-info/SOURCES.txt
UsbLamp.egg-info/dependency_links.txt
UsbLamp.egg-info/requires.txt
UsbLamp.egg-info/top_level.txt
scripts/usblamp
usblamp/__init__.py
usblamp/color.py
usblamp/usblamp.py