Metadata-Version: 1.1
Name: UsbLamp
Version: 0.1
Summary: WebMail Notifier python script
Home-page: UNKNOWN
Author: Pierre Rambaud (GoT)
Author-email: pierre.rambaud86@gmail.com
License: GPLv3
Platform: UNKNOWN
Requires: pyusb (>= 1.0.0b1)
